Workbook
Name Aporte: App!$D$18:$D$18
Name qtd_anos: App!$D$19:$D$19
Name rendimentoCarteira: App!$D$13:$D$13
Name salario: App!$D$12:$D$12
Name sugestao_invest: App!$D$14:$D$14
Name taxa_mensal: App!$D$20:$D$20

Sheet App
B11: Configurações
B12: Salário | D12: 5000
B13: Rendimento da carteira | D13: 0.0087
B14: Sugestão de Investimento | D14: =D12*30% -> 1500
B17: Investimento Mensal
B18: Quanto investir por mes? | D18: 500
B19: Por quantos anos? | D19: 5
B20: Taxa de rendimento mensal | D20: 0.01079
B21: Patrimonio acumulado | D21: {=FV(taxa_mensal,qtd_anos*12,Aporte*-1)} -> 41888.457
B22: Dividendos mensais | D22: {=D21*rendimentoCarteira} -> 364.42958
B25: Cenários | D25: Dividendos
A26: 2 | B26: Quanto em 2 anos? | C26: =FV($D$20,$A26*12,$D$18*-1) -> 13613.814 | D26: {=C26*rendimentoCarteira} -> 118.44018
A27: 5 | B27: Quanto em 5 anos? | C27: =FV($D$20,$A27*12,$D$18*-1) -> 41888.457 | D27: {=C27*rendimentoCarteira} -> 364.42958
A28: 10 | B28: Quanto em 10 anos? | C28: =FV($D$20,$A28*12,$D$18*-1) -> 121642.11 | D28: {=C28*rendimentoCarteira} -> 1058.2863
A29: 20 | B29: Quanto em 20 anos? | C29: =FV($D$20,$A29*12,$D$18*-1) -> 562599.2 | D29: {=C29*rendimentoCarteira} -> 4894.613
A30: 30 | B30: Quanto em 30 anos? | C30: =FV($D$20,$A30*12,$D$18*-1) -> 2161084.8 | D30: {=C30*rendimentoCarteira} -> 18801.438
B33: Perfil | D33: Conservador
B34: valor a ser investido por mes | C34: {=Aporte} -> 500
B36: Tipo de FII | C36: Porcentagem | D36: Valores
B37: Papel | C37: =VLOOKUP($D$33&"-"&B37,'tabela apoio'!$A:$D,4,FALSE) -> 0.3 | D37: =$C$34*C37 -> 150
B38: Tijolo | C38: =VLOOKUP($D$33&"-"&B38,'tabela apoio'!$A:$D,4,FALSE) -> 0.5 | D38: =$C$34*C38 -> 250
B39: Hibrido | C39: =VLOOKUP($D$33&"-"&B39,'tabela apoio'!$A:$D,4,FALSE) -> 0.1 | D39: =$C$34*C39 -> 50
B40: FOFs | C40: =VLOOKUP($D$33&"-"&B40,'tabela apoio'!$A:$D,4,FALSE) -> 0.1 | D40: =$C$34*C40 -> 50
B41: Desenvolvimento | C41: =VLOOKUP($D$33&"-"&B41,'tabela apoio'!$A:$D,4,FALSE) -> 0 | D41: =$C$34*C41 -> 0
B42: Hotelaria | C42: =VLOOKUP($D$33&"-"&B42,'tabela apoio'!$A:$D,4,FALSE) -> 0 | D42: =$C$34*C42 -> 0

Sheet tabela apoio
A5: Chave | B5: Perfil | C5: Tipo de FII | D5: %
A6: =B6&"-"&C6 -> Conservador-Papel | B6: Conservador | C6: Papel | D6: 0.3
A7: =B7&"-"&C7 -> Conservador-Tijolo | B7: Conservador | C7: Tijolo | D7: 0.5
A8: =B8&"-"&C8 -> Conservador-Hibrido | B8: Conservador | C8: Hibrido | D8: 0.1
A9: =B9&"-"&C9 -> Conservador-FOFs | B9: Conservador | C9: FOFs | D9: 0.1
A10: =B10&"-"&C10 -> Conservador-Desenvolvimento | B10: Conservador | C10: Desenvolvimento | D10: 0
A11: =B11&"-"&C11 -> Conservador-Hotelaria | B11: Conservador | C11: Hotelaria | D11: 0
A12: =B12&"-"&C12 -> Moderado-Papel | B12: Moderado | C12: Papel | D12: 0.32
A13: =B13&"-"&C13 -> Moderado-Tijolo | B13: Moderado | C13: Tijolo | D13: 0.35
A14: =B14&"-"&C14 -> Moderado-Hibrido | B14: Moderado | C14: Hibrido | D14: 0.08
A15: =B15&"-"&C15 -> Moderado-FOFs | B15: Moderado | C15: FOFs | D15: 0.05
A16: =B16&"-"&C16 -> Moderado-Desenvolvimento | B16: Moderado | C16: Desenvolvimento | D16: 0.1
A17: =B17&"-"&C17 -> Moderado-Hotelaria | B17: Moderado | C17: Hotelaria | D17: 0.1
... A23: =B23&"-"&C23 -> Agressivo-Hotelaria | B23: Agressivo | C23: Hotelaria | D23: 0.1
